mcp_openvision/__init__.py
mcp_openvision/__main__.py
mcp_openvision/config.py
mcp_openvision/exceptions.py
mcp_openvision/mcp_openvision_image_analysis.mcp.json
mcp_openvision/server.py
wojons_mcp_openvision-0.6.3.dist-info/METADATA
wojons_mcp_openvision-0.6.3.dist-info/WHEEL
wojons_mcp_openvision-0.6.3.dist-info/entry_points.txt
wojons_mcp_openvision-0.6.3.dist-info/licenses/LICENSE
wojons_mcp_openvision-0.6.3.dist-info/RECORD
