Metadata-Version: 2.4
Name: wojons-mcp-openvision
Version: 0.6.3
Summary: MCP server for image analysis using OpenRouter
Project-URL: Homepage, https://github.com/wojons/mcp-openvision
Project-URL: Bug Tracker, https://github.com/wojons/mcp-openvision/issues
Author: wojons
License: MIT
License-File: LICENSE
Classifier: Development Status :: 4 - Beta
Classifier: Intended Audience :: Developers
Classifier: License :: OSI Approved :: MIT License
Classifier: Programming Language :: Python :: 3
Classifier: Programming Language :: Python :: 3.10
Classifier: Programming Language :: Python :: 3.11
Classifier: Topic :: Scientific/Engineering :: Artificial Intelligence
Requires-Python: >=3.10
Requires-Dist: mcp>=1.6.0
Requires-Dist: openai
Requires-Dist: pillow
Requires-Dist: requests
Provides-Extra: dev
Requires-Dist: black; extra == 'dev'
Requires-Dist: isort; extra == 'dev'
Requires-Dist: pytest; extra == 'dev'
Requires-Dist: pytest-asyncio; extra == 'dev'
